
opcode=3(iconst_0)	,pushnum=1,lineinfo=trace.ControlTest#fail#33#0,nextinst=1,pushtype=int,pushvalue=0
opcode=184(invokestatic)	,calltype=(I)I,callclass=trace.ControlTest,callname=foo,lineinfo=trace.ControlTest#fail#33#1,nextinst=4
opcode=3(iconst_0)	,pushnum=1,lineinfo=trace.ControlTest#foo#7#0,nextinst=1,pushtype=int,pushvalue=0
opcode=60(istore_1)	,popnum=1,store=1,lineinfo=trace.ControlTest#foo#7#1,nextinst=2
opcode=167(goto)	,branchbyte=31,lineinfo=trace.ControlTest#foo#8#2,nextinst=5
opcode=26(iload_0)	,pushnum=1,load=0,lineinfo=trace.ControlTest#foo#8#33,nextinst=34,pushtype=int,pushvalue=0
opcode=16(bipush)	,pushnum=1,lineinfo=trace.ControlTest#foo#8#34,nextinst=36,pushtype=byte,pushvalue=10
opcode=161(if_icmplt)	,popnum=2,branchbyte=-31,lineinfo=trace.ControlTest#foo#8#36,nextinst=39
opcode=26(iload_0)	,pushnum=1,load=0,lineinfo=trace.ControlTest#foo#10#5,nextinst=6,pushtype=int,pushvalue=0
opcode=8(iconst_5)	,pushnum=1,lineinfo=trace.ControlTest#foo#10#6,nextinst=7,pushtype=int,pushvalue=5
opcode=164(if_icmple)	,popnum=2,branchbyte=20,lineinfo=trace.ControlTest#foo#10#7,nextinst=10
opcode=132(iinc)	,VAR=1,CONST=156,lineinfo=trace.ControlTest#foo#19#27,nextinst=30
opcode=132(iinc)	,VAR=0,CONST=1,lineinfo=trace.ControlTest#foo#21#30,nextinst=33
opcode=26(iload_0)	,pushnum=1,load=0,lineinfo=trace.ControlTest#foo#8#33,nextinst=34,pushtype=int,pushvalue=1
opcode=16(bipush)	,pushnum=1,lineinfo=trace.ControlTest#foo#8#34,nextinst=36,pushtype=byte,pushvalue=10
opcode=161(if_icmplt)	,popnum=2,branchbyte=-31,lineinfo=trace.ControlTest#foo#8#36,nextinst=39
opcode=26(iload_0)	,pushnum=1,load=0,lineinfo=trace.ControlTest#foo#10#5,nextinst=6,pushtype=int,pushvalue=1
opcode=8(iconst_5)	,pushnum=1,lineinfo=trace.ControlTest#foo#10#6,nextinst=7,pushtype=int,pushvalue=5
opcode=164(if_icmple)	,popnum=2,branchbyte=20,lineinfo=trace.ControlTest#foo#10#7,nextinst=10
opcode=132(iinc)	,VAR=1,CONST=156,lineinfo=trace.ControlTest#foo#19#27,nextinst=30
opcode=132(iinc)	,VAR=0,CONST=1,lineinfo=trace.ControlTest#foo#21#30,nextinst=33
opcode=26(iload_0)	,pushnum=1,load=0,lineinfo=trace.ControlTest#foo#8#33,nextinst=34,pushtype=int,pushvalue=2
opcode=16(bipush)	,pushnum=1,lineinfo=trace.ControlTest#foo#8#34,nextinst=36,pushtype=byte,pushvalue=10
opcode=161(if_icmplt)	,popnum=2,branchbyte=-31,lineinfo=trace.ControlTest#foo#8#36,nextinst=39
opcode=26(iload_0)	,pushnum=1,load=0,lineinfo=trace.ControlTest#foo#10#5,nextinst=6,pushtype=int,pushvalue=2
opcode=8(iconst_5)	,pushnum=1,lineinfo=trace.ControlTest#foo#10#6,nextinst=7,pushtype=int,pushvalue=5
opcode=164(if_icmple)	,popnum=2,branchbyte=20,lineinfo=trace.ControlTest#foo#10#7,nextinst=10
opcode=132(iinc)	,VAR=1,CONST=156,lineinfo=trace.ControlTest#foo#19#27,nextinst=30
opcode=132(iinc)	,VAR=0,CONST=1,lineinfo=trace.ControlTest#foo#21#30,nextinst=33
opcode=26(iload_0)	,pushnum=1,load=0,lineinfo=trace.ControlTest#foo#8#33,nextinst=34,pushtype=int,pushvalue=3
opcode=16(bipush)	,pushnum=1,lineinfo=trace.ControlTest#foo#8#34,nextinst=36,pushtype=byte,pushvalue=10
opcode=161(if_icmplt)	,popnum=2,branchbyte=-31,lineinfo=trace.ControlTest#foo#8#36,nextinst=39
opcode=26(iload_0)	,pushnum=1,load=0,lineinfo=trace.ControlTest#foo#10#5,nextinst=6,pushtype=int,pushvalue=3
opcode=8(iconst_5)	,pushnum=1,lineinfo=trace.ControlTest#foo#10#6,nextinst=7,pushtype=int,pushvalue=5
opcode=164(if_icmple)	,popnum=2,branchbyte=20,lineinfo=trace.ControlTest#foo#10#7,nextinst=10
opcode=132(iinc)	,VAR=1,CONST=156,lineinfo=trace.ControlTest#foo#19#27,nextinst=30
opcode=132(iinc)	,VAR=0,CONST=1,lineinfo=trace.ControlTest#foo#21#30,nextinst=33
opcode=26(iload_0)	,pushnum=1,load=0,lineinfo=trace.ControlTest#foo#8#33,nextinst=34,pushtype=int,pushvalue=4
opcode=16(bipush)	,pushnum=1,lineinfo=trace.ControlTest#foo#8#34,nextinst=36,pushtype=byte,pushvalue=10
opcode=161(if_icmplt)	,popnum=2,branchbyte=-31,lineinfo=trace.ControlTest#foo#8#36,nextinst=39
opcode=26(iload_0)	,pushnum=1,load=0,lineinfo=trace.ControlTest#foo#10#5,nextinst=6,pushtype=int,pushvalue=4
opcode=8(iconst_5)	,pushnum=1,lineinfo=trace.ControlTest#foo#10#6,nextinst=7,pushtype=int,pushvalue=5
opcode=164(if_icmple)	,popnum=2,branchbyte=20,lineinfo=trace.ControlTest#foo#10#7,nextinst=10
opcode=132(iinc)	,VAR=1,CONST=156,lineinfo=trace.ControlTest#foo#19#27,nextinst=30
opcode=132(iinc)	,VAR=0,CONST=1,lineinfo=trace.ControlTest#foo#21#30,nextinst=33
opcode=26(iload_0)	,pushnum=1,load=0,lineinfo=trace.ControlTest#foo#8#33,nextinst=34,pushtype=int,pushvalue=5
opcode=16(bipush)	,pushnum=1,lineinfo=trace.ControlTest#foo#8#34,nextinst=36,pushtype=byte,pushvalue=10
opcode=161(if_icmplt)	,popnum=2,branchbyte=-31,lineinfo=trace.ControlTest#foo#8#36,nextinst=39
opcode=26(iload_0)	,pushnum=1,load=0,lineinfo=trace.ControlTest#foo#10#5,nextinst=6,pushtype=int,pushvalue=5
opcode=8(iconst_5)	,pushnum=1,lineinfo=trace.ControlTest#foo#10#6,nextinst=7,pushtype=int,pushvalue=5
opcode=164(if_icmple)	,popnum=2,branchbyte=20,lineinfo=trace.ControlTest#foo#10#7,nextinst=10
opcode=132(iinc)	,VAR=1,CONST=156,lineinfo=trace.ControlTest#foo#19#27,nextinst=30
opcode=132(iinc)	,VAR=0,CONST=1,lineinfo=trace.ControlTest#foo#21#30,nextinst=33
opcode=26(iload_0)	,pushnum=1,load=0,lineinfo=trace.ControlTest#foo#8#33,nextinst=34,pushtype=int,pushvalue=6
opcode=16(bipush)	,pushnum=1,lineinfo=trace.ControlTest#foo#8#34,nextinst=36,pushtype=byte,pushvalue=10
opcode=161(if_icmplt)	,popnum=2,branchbyte=-31,lineinfo=trace.ControlTest#foo#8#36,nextinst=39
opcode=26(iload_0)	,pushnum=1,load=0,lineinfo=trace.ControlTest#foo#10#5,nextinst=6,pushtype=int,pushvalue=6
opcode=8(iconst_5)	,pushnum=1,lineinfo=trace.ControlTest#foo#10#6,nextinst=7,pushtype=int,pushvalue=5
opcode=164(if_icmple)	,popnum=2,branchbyte=20,lineinfo=trace.ControlTest#foo#10#7,nextinst=10
opcode=26(iload_0)	,pushnum=1,load=0,lineinfo=trace.ControlTest#foo#11#10,nextinst=11,pushtype=int,pushvalue=6
opcode=16(bipush)	,pushnum=1,lineinfo=trace.ControlTest#foo#11#11,nextinst=13,pushtype=byte,pushvalue=8
opcode=164(if_icmple)	,popnum=2,branchbyte=8,lineinfo=trace.ControlTest#foo#11#13,nextinst=16
opcode=132(iinc)	,VAR=1,CONST=1,lineinfo=trace.ControlTest#foo#15#21,nextinst=24
opcode=167(goto)	,branchbyte=6,lineinfo=trace.ControlTest#foo#17#24,nextinst=27
opcode=132(iinc)	,VAR=0,CONST=1,lineinfo=trace.ControlTest#foo#21#30,nextinst=33
opcode=26(iload_0)	,pushnum=1,load=0,lineinfo=trace.ControlTest#foo#8#33,nextinst=34,pushtype=int,pushvalue=7
opcode=16(bipush)	,pushnum=1,lineinfo=trace.ControlTest#foo#8#34,nextinst=36,pushtype=byte,pushvalue=10
opcode=161(if_icmplt)	,popnum=2,branchbyte=-31,lineinfo=trace.ControlTest#foo#8#36,nextinst=39
opcode=26(iload_0)	,pushnum=1,load=0,lineinfo=trace.ControlTest#foo#10#5,nextinst=6,pushtype=int,pushvalue=7
opcode=8(iconst_5)	,pushnum=1,lineinfo=trace.ControlTest#foo#10#6,nextinst=7,pushtype=int,pushvalue=5
opcode=164(if_icmple)	,popnum=2,branchbyte=20,lineinfo=trace.ControlTest#foo#10#7,nextinst=10
opcode=26(iload_0)	,pushnum=1,load=0,lineinfo=trace.ControlTest#foo#11#10,nextinst=11,pushtype=int,pushvalue=7
opcode=16(bipush)	,pushnum=1,lineinfo=trace.ControlTest#foo#11#11,nextinst=13,pushtype=byte,pushvalue=8
opcode=164(if_icmple)	,popnum=2,branchbyte=8,lineinfo=trace.ControlTest#foo#11#13,nextinst=16
opcode=132(iinc)	,VAR=1,CONST=1,lineinfo=trace.ControlTest#foo#15#21,nextinst=24
opcode=167(goto)	,branchbyte=6,lineinfo=trace.ControlTest#foo#17#24,nextinst=27
opcode=132(iinc)	,VAR=0,CONST=1,lineinfo=trace.ControlTest#foo#21#30,nextinst=33
opcode=26(iload_0)	,pushnum=1,load=0,lineinfo=trace.ControlTest#foo#8#33,nextinst=34,pushtype=int,pushvalue=8
opcode=16(bipush)	,pushnum=1,lineinfo=trace.ControlTest#foo#8#34,nextinst=36,pushtype=byte,pushvalue=10
opcode=161(if_icmplt)	,popnum=2,branchbyte=-31,lineinfo=trace.ControlTest#foo#8#36,nextinst=39
opcode=26(iload_0)	,pushnum=1,load=0,lineinfo=trace.ControlTest#foo#10#5,nextinst=6,pushtype=int,pushvalue=8
opcode=8(iconst_5)	,pushnum=1,lineinfo=trace.ControlTest#foo#10#6,nextinst=7,pushtype=int,pushvalue=5
opcode=164(if_icmple)	,popnum=2,branchbyte=20,lineinfo=trace.ControlTest#foo#10#7,nextinst=10
opcode=26(iload_0)	,pushnum=1,load=0,lineinfo=trace.ControlTest#foo#11#10,nextinst=11,pushtype=int,pushvalue=8
opcode=16(bipush)	,pushnum=1,lineinfo=trace.ControlTest#foo#11#11,nextinst=13,pushtype=byte,pushvalue=8
opcode=164(if_icmple)	,popnum=2,branchbyte=8,lineinfo=trace.ControlTest#foo#11#13,nextinst=16
opcode=132(iinc)	,VAR=1,CONST=1,lineinfo=trace.ControlTest#foo#15#21,nextinst=24
opcode=167(goto)	,branchbyte=6,lineinfo=trace.ControlTest#foo#17#24,nextinst=27
opcode=132(iinc)	,VAR=0,CONST=1,lineinfo=trace.ControlTest#foo#21#30,nextinst=33
opcode=26(iload_0)	,pushnum=1,load=0,lineinfo=trace.ControlTest#foo#8#33,nextinst=34,pushtype=int,pushvalue=9
opcode=16(bipush)	,pushnum=1,lineinfo=trace.ControlTest#foo#8#34,nextinst=36,pushtype=byte,pushvalue=10
opcode=161(if_icmplt)	,popnum=2,branchbyte=-31,lineinfo=trace.ControlTest#foo#8#36,nextinst=39
opcode=26(iload_0)	,pushnum=1,load=0,lineinfo=trace.ControlTest#foo#10#5,nextinst=6,pushtype=int,pushvalue=9
opcode=8(iconst_5)	,pushnum=1,lineinfo=trace.ControlTest#foo#10#6,nextinst=7,pushtype=int,pushvalue=5
opcode=164(if_icmple)	,popnum=2,branchbyte=20,lineinfo=trace.ControlTest#foo#10#7,nextinst=10
opcode=26(iload_0)	,pushnum=1,load=0,lineinfo=trace.ControlTest#foo#11#10,nextinst=11,pushtype=int,pushvalue=9
opcode=16(bipush)	,pushnum=1,lineinfo=trace.ControlTest#foo#11#11,nextinst=13,pushtype=byte,pushvalue=8
opcode=164(if_icmple)	,popnum=2,branchbyte=8,lineinfo=trace.ControlTest#foo#11#13,nextinst=16
opcode=27(iload_1)	,pushnum=1,load=1,lineinfo=trace.ControlTest#foo#12#16,nextinst=17,pushtype=int,pushvalue=-597
opcode=16(bipush)	,pushnum=1,lineinfo=trace.ControlTest#foo#12#17,nextinst=19,pushtype=byte,pushvalue=10
opcode=96(iadd)	,popnum=2,pushnum=1,lineinfo=trace.ControlTest#foo#12#19,nextinst=20,pushtype=int,pushvalue=-587
opcode=172(ireturn)	,popnum=-1,lineinfo=trace.ControlTest#foo#12#20,nextinst=21
opcode=17(sipush)	,pushnum=1,lineinfo=trace.ControlTest#fail#33#4,nextinst=7,pushtype=short,pushvalue=-588
opcode=184(invokestatic)	,calltype=(II)V,callclass=org.junit.jupiter.api.Assertions,callname=assertEquals,lineinfo=trace.ControlTest#fail#33#7,nextinst=10