
opcode=3(iconst_0)	,pushnum=1,lineinfo=trace.WhileTest#foo#7#0,nextinst=1
opcode=61(istore_2)	,popnum=1,store=2,lineinfo=trace.WhileTest#foo#7#1,nextinst=2
opcode=26(iload_0)	,pushnum=1,load=0,lineinfo=trace.WhileTest#foo#8#2,nextinst=3
opcode=16(bipush)	,pushnum=1,lineinfo=trace.WhileTest#foo#8#3,nextinst=5
opcode=162(if_icmpge)	,popnum=2,branchbyte=28,lineinfo=trace.WhileTest#foo#8#5,nextinst=8
opcode=26(iload_0)	,pushnum=1,load=0,lineinfo=trace.WhileTest#foo#8#8,nextinst=9
opcode=27(iload_1)	,pushnum=1,load=1,lineinfo=trace.WhileTest#foo#8#9,nextinst=10
opcode=104(imul)	,popnum=2,pushnum=1,lineinfo=trace.WhileTest#foo#8#10,nextinst=11
opcode=16(bipush)	,pushnum=1,lineinfo=trace.WhileTest#foo#8#11,nextinst=13
opcode=162(if_icmpge)	,popnum=2,branchbyte=20,lineinfo=trace.WhileTest#foo#8#13,nextinst=16
opcode=28(iload_2)	,pushnum=1,load=2,lineinfo=trace.WhileTest#foo#11#16,nextinst=17
opcode=26(iload_0)	,pushnum=1,load=0,lineinfo=trace.WhileTest#foo#11#17,nextinst=18
opcode=27(iload_1)	,pushnum=1,load=1,lineinfo=trace.WhileTest#foo#11#18,nextinst=19
opcode=104(imul)	,popnum=2,pushnum=1,lineinfo=trace.WhileTest#foo#11#19,nextinst=20
opcode=96(iadd)	,popnum=2,pushnum=1,lineinfo=trace.WhileTest#foo#11#20,nextinst=21
opcode=61(istore_2)	,popnum=1,store=2,lineinfo=trace.WhileTest#foo#11#21,nextinst=22
opcode=26(iload_0)	,pushnum=1,load=0,lineinfo=trace.WhileTest#foo#12#22,nextinst=23
opcode=4(iconst_1)	,pushnum=1,lineinfo=trace.WhileTest#foo#12#23,nextinst=24
opcode=96(iadd)	,popnum=2,pushnum=1,lineinfo=trace.WhileTest#foo#12#24,nextinst=25
opcode=59(istore_0)	,popnum=1,store=0,lineinfo=trace.WhileTest#foo#12#25,nextinst=26
opcode=27(iload_1)	,pushnum=1,load=1,lineinfo=trace.WhileTest#foo#13#26,nextinst=27
opcode=4(iconst_1)	,pushnum=1,lineinfo=trace.WhileTest#foo#13#27,nextinst=28
opcode=100(isub)	,popnum=2,pushnum=1,lineinfo=trace.WhileTest#foo#13#28,nextinst=29
opcode=60(istore_1)	,popnum=1,store=1,lineinfo=trace.WhileTest#foo#13#29,nextinst=30
opcode=167(goto)	,branchbyte=-28,lineinfo=trace.WhileTest#foo#13#30,nextinst=33
opcode=28(iload_2)	,pushnum=1,load=2,lineinfo=trace.WhileTest#foo#15#33,nextinst=34
opcode=172(ireturn)	,popnum=-1,lineinfo=trace.WhileTest#foo#15#34,nextinst=-1
opcode=16(bipush)	,pushnum=1,lineinfo=trace.WhileTest#pass#20#0,nextinst=2
opcode=5(iconst_2)	,pushnum=1,lineinfo=trace.WhileTest#pass#20#2,nextinst=3
opcode=184(invokestatic)	,calltype=(II)I,callclass=trace.WhileTest,callname=foo,lineinfo=trace.WhileTest#pass#20#3,nextinst=6
opcode=16(bipush)	,pushnum=1,lineinfo=trace.WhileTest#pass#20#6,nextinst=8
opcode=184(invokestatic)	,calltype=(II)V,callclass=org.junit.jupiter.api.Assertions,callname=assertEquals,lineinfo=trace.WhileTest#pass#20#8,nextinst=11
opcode=177(return)	,popnum=-1,lineinfo=trace.WhileTest#pass#21#11,nextinst=-1
opcode=7(iconst_4)	,pushnum=1,lineinfo=trace.WhileTest#fail#25#0,nextinst=1
opcode=16(bipush)	,pushnum=1,lineinfo=trace.WhileTest#fail#25#1,nextinst=3
opcode=184(invokestatic)	,calltype=(II)I,callclass=trace.WhileTest,callname=foo,lineinfo=trace.WhileTest#fail#25#3,nextinst=6
opcode=3(iconst_0)	,pushnum=1,lineinfo=trace.WhileTest#fail#25#6,nextinst=7
opcode=184(invokestatic)	,calltype=(II)V,callclass=org.junit.jupiter.api.Assertions,callname=assertEquals,lineinfo=trace.WhileTest#fail#25#7,nextinst=10
opcode=177(return)	,popnum=-1,lineinfo=trace.WhileTest#fail#26#10,nextinst=-1