
opcode=27(iload_1)	,pushnum=1,load=1,lineinfo=trace.SwitchTest#f#9#0,nextinst=1
opcode=170(tableswitch)	,popnum=1,default=50,switch=0:31;1:35;2:39;3:43;,lineinfo=trace.SwitchTest#f#9#1,nextinst=32
opcode=27(iload_1)	,pushnum=1,load=1,lineinfo=trace.SwitchTest#f#11#32,nextinst=33
opcode=4(iconst_1)	,pushnum=1,lineinfo=trace.SwitchTest#f#11#33,nextinst=34
opcode=96(iadd)	,popnum=2,pushnum=1,lineinfo=trace.SwitchTest#f#11#34,nextinst=35
opcode=60(istore_1)	,popnum=1,store=1,lineinfo=trace.SwitchTest#f#11#35,nextinst=36
opcode=27(iload_1)	,pushnum=1,load=1,lineinfo=trace.SwitchTest#f#13#36,nextinst=37
opcode=5(iconst_2)	,pushnum=1,lineinfo=trace.SwitchTest#f#13#37,nextinst=38
opcode=96(iadd)	,popnum=2,pushnum=1,lineinfo=trace.SwitchTest#f#13#38,nextinst=39
opcode=60(istore_1)	,popnum=1,store=1,lineinfo=trace.SwitchTest#f#13#39,nextinst=40
opcode=27(iload_1)	,pushnum=1,load=1,lineinfo=trace.SwitchTest#f#15#40,nextinst=41
opcode=6(iconst_3)	,pushnum=1,lineinfo=trace.SwitchTest#f#15#41,nextinst=42
opcode=96(iadd)	,popnum=2,pushnum=1,lineinfo=trace.SwitchTest#f#15#42,nextinst=43
opcode=60(istore_1)	,popnum=1,store=1,lineinfo=trace.SwitchTest#f#15#43,nextinst=44
opcode=27(iload_1)	,pushnum=1,load=1,lineinfo=trace.SwitchTest#f#17#44,nextinst=45
opcode=7(iconst_4)	,pushnum=1,lineinfo=trace.SwitchTest#f#17#45,nextinst=46
opcode=96(iadd)	,popnum=2,pushnum=1,lineinfo=trace.SwitchTest#f#17#46,nextinst=47
opcode=60(istore_1)	,popnum=1,store=1,lineinfo=trace.SwitchTest#f#17#47,nextinst=48
opcode=167(goto)	,branchbyte=14,lineinfo=trace.SwitchTest#f#18#48,nextinst=51
opcode=27(iload_1)	,pushnum=1,load=1,lineinfo=trace.SwitchTest#f#20#51,nextinst=52
opcode=156(ifge)	,popnum=1,branchbyte=7,lineinfo=trace.SwitchTest#f#20#52,nextinst=55
opcode=27(iload_1)	,pushnum=1,load=1,lineinfo=trace.SwitchTest#f#20#55,nextinst=56
opcode=167(goto)	,branchbyte=5,lineinfo=trace.SwitchTest#f#20#56,nextinst=59
opcode=27(iload_1)	,pushnum=1,load=1,lineinfo=trace.SwitchTest#f#20#59,nextinst=60
opcode=116(ineg)	,popnum=1,pushnum=1,lineinfo=trace.SwitchTest#f#20#60,nextinst=61
opcode=60(istore_1)	,popnum=1,store=1,lineinfo=trace.SwitchTest#f#20#61,nextinst=62
opcode=27(iload_1)	,pushnum=1,load=1,lineinfo=trace.SwitchTest#f#22#62,nextinst=63
opcode=171(lookupswitch)	,popnum=1,default=60,switch=2:41;34:45;56:49;78:53;,lineinfo=trace.SwitchTest#f#22#63,nextinst=104
opcode=27(iload_1)	,pushnum=1,load=1,lineinfo=trace.SwitchTest#f#24#104,nextinst=105
opcode=4(iconst_1)	,pushnum=1,lineinfo=trace.SwitchTest#f#24#105,nextinst=106
opcode=96(iadd)	,popnum=2,pushnum=1,lineinfo=trace.SwitchTest#f#24#106,nextinst=107
opcode=60(istore_1)	,popnum=1,store=1,lineinfo=trace.SwitchTest#f#24#107,nextinst=108
opcode=27(iload_1)	,pushnum=1,load=1,lineinfo=trace.SwitchTest#f#26#108,nextinst=109
opcode=5(iconst_2)	,pushnum=1,lineinfo=trace.SwitchTest#f#26#109,nextinst=110
opcode=96(iadd)	,popnum=2,pushnum=1,lineinfo=trace.SwitchTest#f#26#110,nextinst=111
opcode=60(istore_1)	,popnum=1,store=1,lineinfo=trace.SwitchTest#f#26#111,nextinst=112
opcode=27(iload_1)	,pushnum=1,load=1,lineinfo=trace.SwitchTest#f#28#112,nextinst=113
opcode=6(iconst_3)	,pushnum=1,lineinfo=trace.SwitchTest#f#28#113,nextinst=114
opcode=96(iadd)	,popnum=2,pushnum=1,lineinfo=trace.SwitchTest#f#28#114,nextinst=115
opcode=60(istore_1)	,popnum=1,store=1,lineinfo=trace.SwitchTest#f#28#115,nextinst=116
opcode=27(iload_1)	,pushnum=1,load=1,lineinfo=trace.SwitchTest#f#30#116,nextinst=117
opcode=7(iconst_4)	,pushnum=1,lineinfo=trace.SwitchTest#f#30#117,nextinst=118
opcode=96(iadd)	,popnum=2,pushnum=1,lineinfo=trace.SwitchTest#f#30#118,nextinst=119
opcode=60(istore_1)	,popnum=1,store=1,lineinfo=trace.SwitchTest#f#30#119,nextinst=120
opcode=167(goto)	,branchbyte=14,lineinfo=trace.SwitchTest#f#31#120,nextinst=123
opcode=27(iload_1)	,pushnum=1,load=1,lineinfo=trace.SwitchTest#f#33#123,nextinst=124
opcode=156(ifge)	,popnum=1,branchbyte=7,lineinfo=trace.SwitchTest#f#33#124,nextinst=127
opcode=27(iload_1)	,pushnum=1,load=1,lineinfo=trace.SwitchTest#f#33#127,nextinst=128
opcode=167(goto)	,branchbyte=5,lineinfo=trace.SwitchTest#f#33#128,nextinst=131
opcode=27(iload_1)	,pushnum=1,load=1,lineinfo=trace.SwitchTest#f#33#131,nextinst=132
opcode=116(ineg)	,popnum=1,pushnum=1,lineinfo=trace.SwitchTest#f#33#132,nextinst=133
opcode=60(istore_1)	,popnum=1,store=1,lineinfo=trace.SwitchTest#f#33#133,nextinst=134
opcode=27(iload_1)	,pushnum=1,load=1,lineinfo=trace.SwitchTest#f#35#134,nextinst=135
opcode=172(ireturn)	,popnum=-1,lineinfo=trace.SwitchTest#f#35#135,nextinst=-1


opcode=16(bipush)	,pushnum=1,lineinfo=trace.SwitchTest#pass#40#0,nextinst=2
opcode=42(aload_0)	,pushnum=1,load=0,lineinfo=trace.SwitchTest#pass#40#2,nextinst=3
opcode=5(iconst_2)	,pushnum=1,lineinfo=trace.SwitchTest#pass#40#3,nextinst=4
opcode=182(invokevirtual)	,calltype=(I)I,callclass=trace.SwitchTest,callname=f,lineinfo=trace.SwitchTest#pass#40#4,nextinst=7
opcode=184(invokestatic)	,calltype=(II)V,callclass=org.junit.jupiter.api.Assertions,callname=assertEquals,lineinfo=trace.SwitchTest#pass#40#7,nextinst=10
opcode=177(return)	,popnum=-1,lineinfo=trace.SwitchTest#pass#42#10,nextinst=-1
opcode=6(iconst_3)	,pushnum=1,lineinfo=trace.SwitchTest#fail#46#0,nextinst=1
opcode=42(aload_0)	,pushnum=1,load=0,lineinfo=trace.SwitchTest#fail#46#1,nextinst=2
opcode=3(iconst_0)	,pushnum=1,lineinfo=trace.SwitchTest#fail#46#2,nextinst=3
opcode=182(invokevirtual)	,calltype=(I)I,callclass=trace.SwitchTest,callname=f,lineinfo=trace.SwitchTest#fail#46#3,nextinst=6
opcode=184(invokestatic)	,calltype=(II)V,callclass=org.junit.jupiter.api.Assertions,callname=assertEquals,lineinfo=trace.SwitchTest#fail#46#6,nextinst=9
opcode=177(return)	,popnum=-1,lineinfo=trace.SwitchTest#fail#48#9,nextinst=-1