
opcode=27(iload_1)	,pushnum=1,load=1,lineinfo=trace.BadReturnTest#fact#10#0,nextinst=1
opcode=157(ifgt)	,popnum=1,branchbyte=5,lineinfo=trace.BadReturnTest#fact#10#1,nextinst=4
opcode=4(iconst_1)	,pushnum=1,lineinfo=trace.BadReturnTest#fact#11#4,nextinst=5
opcode=172(ireturn)	,popnum=-1,lineinfo=trace.BadReturnTest#fact#11#5,nextinst=6
opcode=27(iload_1)	,pushnum=1,load=1,lineinfo=trace.BadReturnTest#fact#12#6,nextinst=7
opcode=5(iconst_2)	,pushnum=1,lineinfo=trace.BadReturnTest#fact#12#7,nextinst=8
opcode=160(if_icmpne)	,popnum=2,branchbyte=6,lineinfo=trace.BadReturnTest#fact#12#8,nextinst=11
opcode=18(ldc)	,pushnum=1,lineinfo=trace.BadReturnTest#fact#13#11,nextinst=13
opcode=172(ireturn)	,popnum=-1,lineinfo=trace.BadReturnTest#fact#13#13,nextinst=14
opcode=27(iload_1)	,pushnum=1,load=1,lineinfo=trace.BadReturnTest#fact#16#14,nextinst=15
opcode=42(aload_0)	,pushnum=1,load=0,lineinfo=trace.BadReturnTest#fact#16#15,nextinst=16
opcode=27(iload_1)	,pushnum=1,load=1,lineinfo=trace.BadReturnTest#fact#16#16,nextinst=17
opcode=4(iconst_1)	,pushnum=1,lineinfo=trace.BadReturnTest#fact#16#17,nextinst=18
opcode=100(isub)	,popnum=2,pushnum=1,lineinfo=trace.BadReturnTest#fact#16#18,nextinst=19
opcode=182(invokevirtual)	,calltype=(I)I,callclass=trace.BadReturnTest,callname=fact,lineinfo=trace.BadReturnTest#fact#16#19,nextinst=22
opcode=104(imul)	,popnum=2,pushnum=1,lineinfo=trace.BadReturnTest#fact#16#22,nextinst=23
opcode=172(ireturn)	,popnum=-1,lineinfo=trace.BadReturnTest#fact#16#23,nextinst=-1
opcode=42(aload_0)	,pushnum=1,load=0,lineinfo=trace.BadReturnTest#pass1#21#0,nextinst=1
opcode=3(iconst_0)	,pushnum=1,lineinfo=trace.BadReturnTest#pass1#21#1,nextinst=2
opcode=182(invokevirtual)	,calltype=(I)I,callclass=trace.BadReturnTest,callname=fact,lineinfo=trace.BadReturnTest#pass1#21#2,nextinst=5
opcode=4(iconst_1)	,pushnum=1,lineinfo=trace.BadReturnTest#pass1#21#5,nextinst=6
opcode=184(invokestatic)	,calltype=(II)V,callclass=org.junit.jupiter.api.Assertions,callname=assertEquals,lineinfo=trace.BadReturnTest#pass1#21#6,nextinst=9
opcode=177(return)	,popnum=-1,lineinfo=trace.BadReturnTest#pass1#22#9,nextinst=-1
opcode=42(aload_0)	,pushnum=1,load=0,lineinfo=trace.BadReturnTest#pass2#26#0,nextinst=1
opcode=4(iconst_1)	,pushnum=1,lineinfo=trace.BadReturnTest#pass2#26#1,nextinst=2
opcode=182(invokevirtual)	,calltype=(I)I,callclass=trace.BadReturnTest,callname=fact,lineinfo=trace.BadReturnTest#pass2#26#2,nextinst=5
opcode=4(iconst_1)	,pushnum=1,lineinfo=trace.BadReturnTest#pass2#26#5,nextinst=6
opcode=184(invokestatic)	,calltype=(II)V,callclass=org.junit.jupiter.api.Assertions,callname=assertEquals,lineinfo=trace.BadReturnTest#pass2#26#6,nextinst=9
opcode=177(return)	,popnum=-1,lineinfo=trace.BadReturnTest#pass2#27#9,nextinst=-1
opcode=42(aload_0)	,pushnum=1,load=0,lineinfo=trace.BadReturnTest#fail#31#0,nextinst=1
opcode=6(iconst_3)	,pushnum=1,lineinfo=trace.BadReturnTest#fail#31#1,nextinst=2
opcode=182(invokevirtual)	,calltype=(I)I,callclass=trace.BadReturnTest,callname=fact,lineinfo=trace.BadReturnTest#fail#31#2,nextinst=5
opcode=16(bipush)	,pushnum=1,lineinfo=trace.BadReturnTest#fail#31#5,nextinst=7
opcode=184(invokestatic)	,calltype=(II)V,callclass=org.junit.jupiter.api.Assertions,callname=assertEquals,lineinfo=trace.BadReturnTest#fail#31#7,nextinst=10
opcode=177(return)	,popnum=-1,lineinfo=trace.BadReturnTest#fail#32#10,nextinst=-1